{
  "fetched_at": "2025-06-15T00:31:01.119488",
  "channel_id": "UC44EBsw3ZiO7qX3gg7sV4Dw",
  "channel_title": "Balitecture",
  "count": 10,
  "videos": [
    {
      "title": "This house embodies modern and minimalist design with a touch of Bali&#39;s tropical style🏝️✨ #villa",
      "video_id": "MUKH8eimvxs",
      "channel_title": "Balitecture",
      "description": "",
      "published_at": "2025-06-14T12:00:39Z",
      "thumbnail_url": "https://i.ytimg.com/vi/MUKH8eimvxs/hqdefault.jpg"
    },
    {
      "title": "Chic home with white pebbles, sculpted bonsai, &amp; a sleek plunge pool under open skies! #homedesign",
      "video_id": "5Wki_k-psIs",
      "channel_title": "Balitecture",
      "description": "",
      "published_at": "2025-06-13T12:00:09Z",
      "thumbnail_url": "https://i.ytimg.com/vi/5Wki_k-psIs/hqdefault.jpg"
    },
    {
      "title": "This villa is where sleek design meets pure fun!✨💯 #luxuryhomes #mansion #realestate #bali",
      "video_id": "lBn4nQs1dgU",
      "channel_title": "Balitecture",
      "description": "",
      "published_at": "2025-06-12T12:01:20Z",
      "thumbnail_url": "https://i.ytimg.com/vi/lBn4nQs1dgU/hqdefault.jpg"
    },
    {
      "title": "The design is incredibly smart, featuring sun loungers with hidden storage! #minimalist #homedesign",
      "video_id": "1K7fEgXkTPo",
      "channel_title": "Balitecture",
      "description": "",
      "published_at": "2025-06-11T11:00:07Z",
      "thumbnail_url": "https://i.ytimg.com/vi/1K7fEgXkTPo/hqdefault.jpg"
    },
    {
      "title": "This place is all about chill vibes and seamless indoor-outdoor living🥰🍃 #housetour #tropicalhouse",
      "video_id": "3duyTxEud9Q",
      "channel_title": "Balitecture",
      "description": "",
      "published_at": "2025-06-10T11:00:13Z",
      "thumbnail_url": "https://i.ytimg.com/vi/3duyTxEud9Q/hqdefault.jpg"
    },
    {
      "title": "This space strikes the perfect balance between cool &amp; chic!😍 #minimalist #housedesign #architecture",
      "video_id": "1tFMnst4U6w",
      "channel_title": "Balitecture",
      "description": "",
      "published_at": "2025-06-06T11:00:05Z",
      "thumbnail_url": "https://i.ytimg.com/vi/1tFMnst4U6w/hqdefault.jpg"
    },
    {
      "title": "Welcome to your effortlessly chic slice of paradise! A fresh Bali villa design🤎#housetour #dreamhome",
      "video_id": "IC2-gxl7ufc",
      "channel_title": "Balitecture",
      "description": "",
      "published_at": "2025-06-04T11:00:28Z",
      "thumbnail_url": "https://i.ytimg.com/vi/IC2-gxl7ufc/hqdefault.jpg"
    },
    {
      "title": "This modern villa nails the “wow” factor with bold geometric lines! A timeless #homedesign ✨💯",
      "video_id": "J-jb2DsPARM",
      "channel_title": "Balitecture",
      "description": "",
      "published_at": "2025-06-04T11:00:35Z",
      "thumbnail_url": "https://i.ytimg.com/vi/J-jb2DsPARM/hqdefault.jpg"
    },
    {
      "title": "Proof That Good Design Feeds the Soul",
      "video_id": "oTfyNWpeaOk",
      "channel_title": "Balitecture",
      "description": "Think hotel perks without the check-in desk: fresh linens, soft towels (yes, pool ones too), bath goodies, kitchen must-haves, and ...",
      "published_at": "2025-06-03T13:01:34Z",
      "thumbnail_url": "https://i.ytimg.com/vi/oTfyNWpeaOk/hqdefault.jpg"
    },
    {
      "title": "This modern house entryway is basically shouting “design goals!”💯 #homedesign #minimalist #home",
      "video_id": "bDUbqjgEFTY",
      "channel_title": "Balitecture",
      "description": "",
      "published_at": "2025-06-02T11:01:04Z",
      "thumbnail_url": "https://i.ytimg.com/vi/bDUbqjgEFTY/hqdefault.jpg"
    }
  ]
}