{
  "fetched_at": "2025-04-20T00:28:25.704350",
  "channel_id": "UC4DavIB24rEr5waVY5AgZLg",
  "channel_title": "Walt Disney Imagineering",
  "count": 10,
  "videos": [
    {
      "title": "You asked, Grek answered. 🤖✨  #NationalRoboticsWeek",
      "video_id": "U1-jt3_XHVo",
      "channel_title": "Walt Disney Imagineering",
      "description": "Over on our Instagram, we let followers ask our BDX Droid their most pressing questions. Here's Grek's answers!",
      "published_at": "2025-04-11T19:01:39Z",
      "thumbnail_url": "https://i.ytimg.com/vi/U1-jt3_XHVo/hqdefault.jpg"
    },
    {
      "title": "Imagineers to name their favorite Disney robot (and droids 🤖) — did yours make the list? 👀✨",
      "video_id": "5YiMfFOdZRY",
      "channel_title": "Walt Disney Imagineering",
      "description": "NationalRoboticsWeek.",
      "published_at": "2025-04-08T19:00:37Z",
      "thumbnail_url": "https://i.ytimg.com/vi/5YiMfFOdZRY/hqdefault.jpg"
    },
    {
      "title": "Every decision you make with concrete is literally set in stone! #imagineering",
      "video_id": "maaR6sENTzw",
      "channel_title": "Walt Disney Imagineering",
      "description": "",
      "published_at": "2025-04-04T19:00:45Z",
      "thumbnail_url": "https://i.ytimg.com/vi/maaR6sENTzw/hqdefault.jpg"
    },
    {
      "title": "Happy birthday to Disney Legend Marc Davis! #imagineering",
      "video_id": "f4WyBxjkrrc",
      "channel_title": "Walt Disney Imagineering",
      "description": "",
      "published_at": "2025-03-31T18:19:21Z",
      "thumbnail_url": "https://i.ytimg.com/vi/f4WyBxjkrrc/hqdefault.jpg"
    },
    {
      "title": "Imagineers recently tested new gameplay elements for Buzz Lightyear&#39;s Space Ranger Spin!",
      "video_id": "wRc-jShphtU",
      "channel_title": "Walt Disney Imagineering",
      "description": "",
      "published_at": "2025-03-26T12:31:00Z",
      "thumbnail_url": "https://i.ytimg.com/vi/wRc-jShphtU/hqdefault.jpg"
    },
    {
      "title": "Our Imagineers find inspiration in many places including classic attractions!",
      "video_id": "_Wh6baMWIWk",
      "channel_title": "Walt Disney Imagineering",
      "description": "",
      "published_at": "2025-03-18T19:05:20Z",
      "thumbnail_url": "https://i.ytimg.com/vi/_Wh6baMWIWk/hqdefault.jpg"
    },
    {
      "title": "30 Years of EPCOT International Flower &amp; Garden Festival Innovation | Great Moments in Imagineering",
      "video_id": "W9o9-nWVq2w",
      "channel_title": "Walt Disney Imagineering",
      "description": "For 30 years, the EPCOT International Flower & Garden Festival has brought Disney characters to life in topiary form in new and ...",
      "published_at": "2025-03-14T16:30:15Z",
      "thumbnail_url": "https://i.ytimg.com/vi/W9o9-nWVq2w/hqdefault.jpg"
    },
    {
      "title": "Want to see something cool? 😎",
      "video_id": "l8WP7489eUQ",
      "channel_title": "Walt Disney Imagineering",
      "description": "waltdisneyimagineering #blainegibson.",
      "published_at": "2025-03-12T19:00:24Z",
      "thumbnail_url": "https://i.ytimg.com/vi/l8WP7489eUQ/hqdefault.jpg"
    },
    {
      "title": "A Stark-sized stamp of approval. ✅ Thanks Robert Downey Jr. #imagineering #disneyparks",
      "video_id": "-0_FlLjT0Gc",
      "channel_title": "Walt Disney Imagineering",
      "description": "",
      "published_at": "2025-03-10T22:14:05Z",
      "thumbnail_url": "https://i.ytimg.com/vi/-0_FlLjT0Gc/hqdefault.jpg"
    },
    {
      "title": "We Call It Imagineering | Let&#39;s Ride",
      "video_id": "IuQPrGLo0QM",
      "channel_title": "Walt Disney Imagineering",
      "description": "This episode takes you behind the scenes to see how rides come to life, including an inside look at Stark Flight Lab coming to ...",
      "published_at": "2025-03-10T15:00:05Z",
      "thumbnail_url": "https://i.ytimg.com/vi/IuQPrGLo0QM/hqdefault.jpg"
    }
  ]
}