{
  "fetched_at": "2025-07-13T00:32:13.601897",
  "channel_id": "UC4JX40jDee_tINbkjycV4Sg",
  "channel_title": "Tech With Tim",
  "count": 10,
  "videos": [
    {
      "title": "The Ultimate FastAPI + React Full Stack Project (Deploy This and You’re Set)",
      "video_id": "_1P0Uqk50Ps",
      "channel_title": "Tech With Tim",
      "description": "In this video, you'll learn how to build a full stack application using FastAPI in Python and JavaScript and React. Now I'll cover ...",
      "published_at": "2025-07-11T15:01:05Z",
      "thumbnail_url": "https://i.ytimg.com/vi/_1P0Uqk50Ps/hqdefault.jpg"
    },
    {
      "title": "The biggest MISTAKE new devs make when applying to jobs",
      "video_id": "_6UpwwxSMPw",
      "channel_title": "Tech With Tim",
      "description": "DevLaunch is my mentorship program where I personally help developers go beyond tutorials, build real-world projects, and ...",
      "published_at": "2025-07-11T11:18:57Z",
      "thumbnail_url": "https://i.ytimg.com/vi/_6UpwwxSMPw/hqdefault.jpg"
    },
    {
      "title": "THIS is why you can&#39;t land a coding job",
      "video_id": "f1TjL7b4NA4",
      "channel_title": "Tech With Tim",
      "description": "DevLaunch is my mentorship program where I personally help developers go beyond tutorials, build real-world projects, and ...",
      "published_at": "2025-07-11T11:14:18Z",
      "thumbnail_url": "https://i.ytimg.com/vi/f1TjL7b4NA4/hqdefault.jpg"
    },
    {
      "title": "Your coding resume is sh*t  Here&#39;s how to fix it",
      "video_id": "BAmeO4DFaIY",
      "channel_title": "Tech With Tim",
      "description": "DevLaunch is my mentorship program where I personally help developers go beyond tutorials, build real-world projects, and ...",
      "published_at": "2025-07-09T06:34:25Z",
      "thumbnail_url": "https://i.ytimg.com/vi/BAmeO4DFaIY/hqdefault.jpg"
    },
    {
      "title": "THIS is why you keep getting ghosted by recruiters",
      "video_id": "fRkxtW12oBI",
      "channel_title": "Tech With Tim",
      "description": "DevLaunch is my mentorship program where I personally help developers go beyond tutorials, build real-world projects, and ...",
      "published_at": "2025-07-04T02:52:09Z",
      "thumbnail_url": "https://i.ytimg.com/vi/fRkxtW12oBI/hqdefault.jpg"
    },
    {
      "title": "If you&#39;re serious about learning programming you need to be doing THIS",
      "video_id": "AcMqasZP1Lg",
      "channel_title": "Tech With Tim",
      "description": "DevLaunch is my mentorship program where I personally help developers go beyond tutorials, build real-world projects, and ...",
      "published_at": "2025-06-26T05:15:32Z",
      "thumbnail_url": "https://i.ytimg.com/vi/AcMqasZP1Lg/hqdefault.jpg"
    },
    {
      "title": "THIS is why a CS degree won&#39;t get you a coding job",
      "video_id": "_yNbcn-WCVo",
      "channel_title": "Tech With Tim",
      "description": "My Software Development Program: ...",
      "published_at": "2025-06-12T04:52:05Z",
      "thumbnail_url": "https://i.ytimg.com/vi/_yNbcn-WCVo/hqdefault.jpg"
    },
    {
      "title": "How to get ahead of 99% of devs in 2025",
      "video_id": "DJqGKv_q3bA",
      "channel_title": "Tech With Tim",
      "description": "My Software Development Program: ...",
      "published_at": "2025-06-09T06:30:06Z",
      "thumbnail_url": "https://i.ytimg.com/vi/DJqGKv_q3bA/hqdefault.jpg"
    },
    {
      "title": "How to become an AI engineer in 2025",
      "video_id": "V529teeIQ5o",
      "channel_title": "Tech With Tim",
      "description": "My Software Development Program: ...",
      "published_at": "2025-05-22T12:40:39Z",
      "thumbnail_url": "https://i.ytimg.com/vi/V529teeIQ5o/hqdefault.jpg"
    },
    {
      "title": "You need to MASTER THIS if you wanna land your dream job in tech",
      "video_id": "kdSxZCztEXA",
      "channel_title": "Tech With Tim",
      "description": "My Software Development Program: ...",
      "published_at": "2025-04-27T20:19:02Z",
      "thumbnail_url": "https://i.ytimg.com/vi/kdSxZCztEXA/hqdefault.jpg"
    }
  ]
}