{
  "fetched_at": "2025-10-26T00:28:54.426919",
  "channel_id": "UC766vkQw0Mz3VtXX5XvXxGQ",
  "channel_title": "Meta Quest ",
  "count": 2,
  "videos": [
    {
      "title": "Get your front row access to @STAYC&#39;s Stay Tuned tour. Tune in tonight at 5pm PT in events Arena",
      "video_id": "ZHfjsSIK2Jg",
      "channel_title": "Meta Quest ",
      "description": "",
      "published_at": "2025-10-24T16:14:18Z",
      "thumbnail_url": "https://i.ytimg.com/vi/ZHfjsSIK2Jg/hqdefault.jpg"
    },
    {
      "title": "Gorn 2 | Fight of the Living Dead Update | Meta Quest Platform",
      "video_id": "mkAblbctIEU",
      "channel_title": "Meta Quest ",
      "description": "October has never been bloodier! GORN 2, the gloriously over-the-top sequel to the VR cult hit GORN, has transformed its brutal ...",
      "published_at": "2025-10-20T19:50:23Z",
      "thumbnail_url": "https://i.ytimg.com/vi/mkAblbctIEU/hqdefault.jpg"
    }
  ]
}