{
  "fetched_at": "2025-11-02T00:29:24.093171",
  "channel_id": "UC766vkQw0Mz3VtXX5XvXxGQ",
  "channel_title": "Meta Quest ",
  "count": 10,
  "videos": [
    {
      "title": "Gorilla Tag | Super Infection Mode Official Trailer | Meta Quest Platform",
      "video_id": "UT8A75Dd6MA",
      "channel_title": "Meta Quest ",
      "description": "Take Infection, and make it SUPER! The rules are same as Infection mode, with a randomly chosen Monke starting out as the ...",
      "published_at": "2025-10-31T18:12:56Z",
      "thumbnail_url": "https://i.ytimg.com/vi/UT8A75Dd6MA/hqdefault.jpg"
    },
    {
      "title": "Beat Saber | Andrew Gold: Spooky Scary Skeletons (Undead Tombstone Remix) | Meta Quest Platform",
      "video_id": "d1INdUX02NA",
      "channel_title": "Meta Quest ",
      "description": "It's officially Halloween season in @BeatSaber! Andrew Gold's iconic \"Spooky Scary Skeletons\" (Undead Tombstone Remix) ...",
      "published_at": "2025-10-30T23:32:11Z",
      "thumbnail_url": "https://i.ytimg.com/vi/d1INdUX02NA/hqdefault.jpg"
    },
    {
      "title": "Little Planet | Official Launch Trailer | Meta Quest Platform",
      "video_id": "ADN9CI6XW_o",
      "channel_title": "Meta Quest ",
      "description": "Get ready to build, connect, and thrive! Little Planet is launching FREE-TO-PLAY out of Early Access on Meta Quest this October ...",
      "published_at": "2025-10-30T21:01:08Z",
      "thumbnail_url": "https://i.ytimg.com/vi/ADN9CI6XW_o/hqdefault.jpg"
    },
    {
      "title": "A Long Survive | Official Trailer | Meta Quest Platform",
      "video_id": "npWCAU5M7jg",
      "channel_title": "Meta Quest ",
      "description": "A Long Survive is a cooperative shooter in which you'll have to survive waves of enemies. Protect the nexus by fortifying your area ...",
      "published_at": "2025-10-30T19:07:40Z",
      "thumbnail_url": "https://i.ytimg.com/vi/npWCAU5M7jg/hqdefault.jpg"
    },
    {
      "title": "Lock and Load. #ZombieArmy",
      "video_id": "v76_zKuOhtA",
      "channel_title": "Meta Quest ",
      "description": "",
      "published_at": "2025-10-29T23:30:21Z",
      "thumbnail_url": "https://i.ytimg.com/vi/v76_zKuOhtA/hqdefault.jpg"
    },
    {
      "title": "Floor Plan 2: Backside Story - Launch Trailer | Meta Quest + Rift Platforms",
      "video_id": "WLpMQow19jI",
      "channel_title": "Meta Quest ",
      "description": "Backside Story is a massive new expansion for Floor Plan 2, including an all-new elevator and more. Available now!",
      "published_at": "2023-06-22T17:00:16Z",
      "thumbnail_url": "https://i.ytimg.com/vi/WLpMQow19jI/hqdefault.jpg"
    },
    {
      "title": "I Expect You To Die 3 | Intro Credits Trailer | Meta Quest 2 + 3 + Pro",
      "video_id": "gHalNCDgHSc",
      "channel_title": "Meta Quest ",
      "description": "Agents, we know you've been waiting for it...the intro credits for IEYTD3, featuring a new soulful song called \"\"Cog in the Machine ...",
      "published_at": "2023-06-14T19:31:23Z",
      "thumbnail_url": "https://i.ytimg.com/vi/gHalNCDgHSc/hqdefault.jpg"
    },
    {
      "title": "5 reasons to get hyped for Meta Quest 3 🙌 What are you most excited about?",
      "video_id": "Cl8CWXhs5T8",
      "channel_title": "Meta Quest ",
      "description": "Sign up to be notified when Quest 3 is available: https://metaque.st/Quest3.",
      "published_at": "2023-06-05T14:22:20Z",
      "thumbnail_url": "https://i.ytimg.com/vi/Cl8CWXhs5T8/hqdefault.jpg"
    },
    {
      "title": "Meta Quest Gaming Showcase | 2023",
      "video_id": "g1XPjUCmhXQ",
      "channel_title": "Meta Quest ",
      "description": "Join us for the Meta Quest Gaming Showcase, featuring new game announcements, gameplay first-looks, updates to existing ...",
      "published_at": "2023-06-01T18:09:45Z",
      "thumbnail_url": "https://i.ytimg.com/vi/g1XPjUCmhXQ/hqdefault.jpg"
    },
    {
      "title": "Introducing Meta Quest 3 | Coming This Fall",
      "video_id": "5AKl_cEB26c",
      "channel_title": "Meta Quest ",
      "description": "Redesigned from the inside out, Meta Quest 3 is the wireless headset that can do it all. Enjoy more than twice the GPU processing ...",
      "published_at": "2023-06-01T16:00:06Z",
      "thumbnail_url": "https://i.ytimg.com/vi/5AKl_cEB26c/hqdefault.jpg"
    }
  ]
}