{
  "fetched_at": "2026-04-05T00:43:54.376334",
  "channel_id": "UC7vVhkEfw4nOGp8TyDk7RcQ",
  "channel_title": "Boston Dynamics",
  "count": 10,
  "videos": [
    {
      "title": "How do you make a reliable backflip? | Boston Dynamics",
      "video_id": "zj07hHJnrto",
      "channel_title": "Boston Dynamics",
      "description": "What goes into preparing for a live performance? Arun highlights the reliability testing that goes into trying a new behavior for ...",
      "published_at": "2026-03-26T15:15:41Z",
      "thumbnail_url": "https://i.ytimg.com/vi/zj07hHJnrto/hqdefault.jpg"
    },
    {
      "title": "Form &amp; Function of Enterprise Humanoid Design | Boston Dynamics Tech Talk | Atlas",
      "video_id": "wL0-Pu_8F0U",
      "channel_title": "Boston Dynamics",
      "description": "The production version of Atlas is a departure from the typical humanoid form factor, favoring industrial utility over human likeness.",
      "published_at": "2026-03-18T20:06:23Z",
      "thumbnail_url": "https://i.ytimg.com/vi/wL0-Pu_8F0U/hqdefault.jpg"
    },
    {
      "title": "What&#39;s your favorite classic Boston Dynamics robot? #bostondynamics #robot",
      "video_id": "U18EHTnvFd4",
      "channel_title": "Boston Dynamics",
      "description": "Two of our product managers share why they love Sandflea and BigDog, and the legacy of innovation inspiring the next wave of ...",
      "published_at": "2026-03-03T16:15:03Z",
      "thumbnail_url": "https://i.ytimg.com/vi/U18EHTnvFd4/hqdefault.jpg"
    },
    {
      "title": "ST Engineering MRAS | Boston Dynamics",
      "video_id": "mH4NLGI64MM",
      "channel_title": "Boston Dynamics",
      "description": "Data powers an organization's digital transformation, and ST Engineering MRAS is leveraging Spot to get a full view of critical ...",
      "published_at": "2026-02-18T14:47:42Z",
      "thumbnail_url": "https://i.ytimg.com/vi/mH4NLGI64MM/hqdefault.jpg"
    },
    {
      "title": "Spot at Cargill | Customer Testimonial Excerpt",
      "video_id": "G8WDv2gm4R8",
      "channel_title": "Boston Dynamics",
      "description": "Cargill's Amsterdam Multiseed facility enlists Spot and Orbit to inspect machinery and perform visual checks, enhanced by all-new ...",
      "published_at": "2026-02-10T16:30:51Z",
      "thumbnail_url": "https://i.ytimg.com/vi/G8WDv2gm4R8/hqdefault.jpg"
    },
    {
      "title": "Atlas Airborne | Boston Dynamics &amp; @rai-inst",
      "video_id": "UNorxwlZlFk",
      "channel_title": "Boston Dynamics",
      "description": "Now that the Atlas enterprise platform is getting to work, the research version gets one last run in the sun. Our engineers made ...",
      "published_at": "2026-02-07T14:00:51Z",
      "thumbnail_url": "https://i.ytimg.com/vi/UNorxwlZlFk/hqdefault.jpg"
    },
    {
      "title": "Spot Cam 2  | Boston Dynamics",
      "video_id": "de06_CLqrM0",
      "channel_title": "Boston Dynamics",
      "description": "Learn about this latest in Spot, Orbit, and our new 5.1 release at: ...",
      "published_at": "2026-01-20T14:56:51Z",
      "thumbnail_url": "https://i.ytimg.com/vi/de06_CLqrM0/hqdefault.jpg"
    },
    {
      "title": "That’s a wrap, Atlas!  #ces2026",
      "video_id": "83SQmj5bF9A",
      "channel_title": "Boston Dynamics",
      "description": "",
      "published_at": "2026-01-10T12:35:39Z",
      "thumbnail_url": "https://i.ytimg.com/vi/83SQmj5bF9A/hqdefault.jpg"
    },
    {
      "title": "Atlas | Product Features | Boston Dynamics",
      "video_id": "rrUHZKlrxms",
      "channel_title": "Boston Dynamics",
      "description": "This short video introduces some of the high level futures of the production version of our Atlas robot. Learn more about Atlas: ...",
      "published_at": "2026-01-05T21:30:13Z",
      "thumbnail_url": "https://i.ytimg.com/vi/rrUHZKlrxms/hqdefault.jpg"
    },
    {
      "title": "The Beginning of Your Tomorrow I Boston Dynamics",
      "video_id": "sd8ivhpjI6g",
      "channel_title": "Boston Dynamics",
      "description": "We're excited to announce the product version of our Atlas® robot. This enterprise-grade humanoid robot offers impressive ...",
      "published_at": "2026-01-05T21:30:07Z",
      "thumbnail_url": "https://i.ytimg.com/vi/sd8ivhpjI6g/hqdefault.jpg"
    }
  ]
}