{
  "fetched_at": "2025-09-14T00:27:49.887950",
  "channel_id": "UCBobmJyzsJ6Ll7UbfhI4iwQ",
  "channel_title": "Unreal Engine",
  "count": 5,
  "videos": [
    {
      "title": "News and Community Spotlight | September 12th, 2025",
      "video_id": "jGu_cDNDfjk",
      "channel_title": "Unreal Engine",
      "description": "News ...",
      "published_at": "2025-09-12T21:38:55Z",
      "thumbnail_url": "https://i.ytimg.com/vi/jGu_cDNDfjk/hqdefault.jpg"
    },
    {
      "title": "Unreal Fellowship: Games 2025 | Sizzle Reel",
      "video_id": "BihpM5I05XM",
      "channel_title": "Unreal Engine",
      "description": "Watch this sizzle reel to see some of the fantastic games created as part of the Unreal Fellowship: Games 2025! The Unreal ...",
      "published_at": "2025-09-12T16:04:44Z",
      "thumbnail_url": "https://i.ytimg.com/vi/BihpM5I05XM/hqdefault.jpg"
    },
    {
      "title": "Sports Broadcast Motion Design Sample | Unreal Engine",
      "video_id": "LQO4Q-1CHyM",
      "channel_title": "Unreal Engine",
      "description": "Dive into a new Unreal Engine sample that provides a fully designed, animated, and rigged project covering a range of broadcast ...",
      "published_at": "2025-09-11T16:17:19Z",
      "thumbnail_url": "https://i.ytimg.com/vi/LQO4Q-1CHyM/hqdefault.jpg"
    },
    {
      "title": "Borderlands 4 | Game Profile | Unreal Engine",
      "video_id": "Yi-aJWVe3wA",
      "channel_title": "Unreal Engine",
      "description": "Watch this video to find out how UE5 features played a key role in delivering the biggest, most ambitious installment yet in the ...",
      "published_at": "2025-09-09T14:29:07Z",
      "thumbnail_url": "https://i.ytimg.com/vi/Yi-aJWVe3wA/hqdefault.jpg"
    },
    {
      "title": "One Asset, Infinite Media: Maximizing IP Value Through Unreal Engine | Unreal Fest Orlando 2025",
      "video_id": "DdCRyE8kgBE",
      "channel_title": "Unreal Engine",
      "description": "In this session recorded at Unreal Fest Orlando 2025, Nathan Riddle of Spacestation Animation demonstrates how the company ...",
      "published_at": "2025-09-09T13:00:23Z",
      "thumbnail_url": "https://i.ytimg.com/vi/DdCRyE8kgBE/hqdefault.jpg"
    }
  ]
}