{
  "fetched_at": "2025-06-01T00:34:03.565216",
  "channel_id": "UCBobmJyzsJ6Ll7UbfhI4iwQ",
  "channel_title": "Unreal Engine",
  "count": 5,
  "videos": [
    {
      "title": "3 Days Until State of Unreal!",
      "video_id": "5TkD_K6ELbc",
      "channel_title": "Unreal Engine",
      "description": "The future of Unreal is on the horizon, let's head towards it together   Join us for the State of Unreal on June 3, where we'll be ...",
      "published_at": "2025-05-31T16:00:22Z",
      "thumbnail_url": "https://i.ytimg.com/vi/5TkD_K6ELbc/hqdefault.jpg"
    },
    {
      "title": "Let’s Chat Fortnite Data API with Birdo",
      "video_id": "-YME2CkHkfc",
      "channel_title": "Unreal Engine",
      "description": "The new Fortnite Data API just dropped, so we're joining Birdo to chat all about it. Don't forget to get your questions in about the ...",
      "published_at": "2025-05-30T20:32:17Z",
      "thumbnail_url": "https://i.ytimg.com/vi/-YME2CkHkfc/hqdefault.jpg"
    },
    {
      "title": "Automotive Sizzle 2025 | Unreal Engine and Twinmotion",
      "video_id": "Ev7LPYVzJdo",
      "channel_title": "Unreal Engine",
      "description": "Watch this video for a thrilling ride through some of the spectacular automotive content that has been created in Unreal Engine ...",
      "published_at": "2025-05-29T18:35:15Z",
      "thumbnail_url": "https://i.ytimg.com/vi/Ev7LPYVzJdo/hqdefault.jpg"
    },
    {
      "title": "A voyage into Spice Frontier’s retro 2D look | Spotlight | Unreal Engine",
      "video_id": "zH4Vc_4Yp0A",
      "channel_title": "Unreal Engine",
      "description": "Find out how Steamroller Animation achieved a 2D, 80s-cartoon aesthetic in Unreal Engine for animated show 'Spice ...",
      "published_at": "2025-05-29T18:19:25Z",
      "thumbnail_url": "https://i.ytimg.com/vi/zH4Vc_4Yp0A/hqdefault.jpg"
    },
    {
      "title": "State of Unreal 2025 Official 4K Livestream I Unreal Fest Orlando",
      "video_id": "AjikvaR0i34",
      "channel_title": "Unreal Engine",
      "description": "Buckle up—it's nearly time for the State of Unreal! We'll be streaming live from Unreal Fest Orlando at 9:30 AM EDT on June 3.",
      "published_at": "2025-04-08T16:09:46Z",
      "thumbnail_url": "https://i.ytimg.com/vi/AjikvaR0i34/hqdefault_live.jpg"
    }
  ]
}