{
  "fetched_at": "2025-10-19T00:30:08.860742",
  "channel_id": "UCcG6zooS9BlSgiT0_ICuD0A",
  "channel_title": "Matt Steffanina",
  "count": 10,
  "videos": [
    {
      "title": "This is the key to life…",
      "video_id": "ZFK5J2-TuBA",
      "channel_title": "Matt Steffanina",
      "description": "",
      "published_at": "2025-03-10T07:39:00Z",
      "thumbnail_url": "https://i.ytimg.com/vi/ZFK5J2-TuBA/hqdefault.jpg"
    },
    {
      "title": "FLASH MOB WEDDING DANCE CHOREOGRAPHY  (Rihanna - We Found Love)",
      "video_id": "vg-9RMvLI7M",
      "channel_title": "Matt Steffanina",
      "description": "Make your first day perfect with our new online wedding dance course! ▷ Take the \"Perfect Wedding Dance\" Online: ...",
      "published_at": "2025-01-27T14:01:10Z",
      "thumbnail_url": "https://i.ytimg.com/vi/vg-9RMvLI7M/hqdefault.jpg"
    },
    {
      "title": "Queens doing queen things",
      "video_id": "qPGhUNd18TQ",
      "channel_title": "Matt Steffanina",
      "description": "Learn How To Dance: http://DNCR.com ▷ INSTAGRAM: https://instagram.com/MattSteffanina ▷ TIK TOK: ...",
      "published_at": "2023-12-27T21:30:04Z",
      "thumbnail_url": "https://i.ytimg.com/vi/qPGhUNd18TQ/hqdefault.jpg"
    },
    {
      "title": "The perfect dance duo",
      "video_id": "Zq-auG9NDoQ",
      "channel_title": "Matt Steffanina",
      "description": "Learn How To Dance: http://DNCR.com ▷ INSTAGRAM: https://instagram.com/MattSteffanina ▷ TIK TOK: ...",
      "published_at": "2023-12-27T18:00:27Z",
      "thumbnail_url": "https://i.ytimg.com/vi/Zq-auG9NDoQ/hqdefault.jpg"
    },
    {
      "title": "Carefully watch their moves",
      "video_id": "Ao-JRFdhn7A",
      "channel_title": "Matt Steffanina",
      "description": "Learn How To Dance: http://DNCR.com ▷ INSTAGRAM: https://instagram.com/MattSteffanina ▷ TIK TOK: ...",
      "published_at": "2023-12-26T21:30:00Z",
      "thumbnail_url": "https://i.ytimg.com/vi/Ao-JRFdhn7A/hqdefault.jpg"
    },
    {
      "title": "Kaycee Rice Marshmello Performance",
      "video_id": "XH9bZHQiY60",
      "channel_title": "Matt Steffanina",
      "description": "Learn How To Dance: http://DNCR.com ▷ INSTAGRAM: https://instagram.com/MattSteffanina ▷ TIK TOK: ...",
      "published_at": "2023-12-26T18:00:15Z",
      "thumbnail_url": "https://i.ytimg.com/vi/XH9bZHQiY60/hqdefault.jpg"
    },
    {
      "title": "Words can&#39;t describe these moves...",
      "video_id": "xWTlQqP0CpA",
      "channel_title": "Matt Steffanina",
      "description": "Learn How To Dance: http://DNCR.com ▷ INSTAGRAM: https://instagram.com/MattSteffanina ▷ TIK TOK: ...",
      "published_at": "2023-12-25T21:30:05Z",
      "thumbnail_url": "https://i.ytimg.com/vi/xWTlQqP0CpA/hqdefault.jpg"
    },
    {
      "title": "Emotional Marshmello Choreography",
      "video_id": "dol5x2fXmFM",
      "channel_title": "Matt Steffanina",
      "description": "Learn How To Dance: http://DNCR.com ▷ INSTAGRAM: https://instagram.com/MattSteffanina ▷ TIK TOK: ...",
      "published_at": "2023-12-25T18:00:28Z",
      "thumbnail_url": "https://i.ytimg.com/vi/dol5x2fXmFM/hqdefault.jpg"
    },
    {
      "title": "Nicole Leano&#39;s Not Real",
      "video_id": "Q4SoBBGt_48",
      "channel_title": "Matt Steffanina",
      "description": "Learn How To Dance: http://DNCR.com ▷ INSTAGRAM: https://instagram.com/MattSteffanina ▷ TIK TOK: ...",
      "published_at": "2023-12-19T18:00:17Z",
      "thumbnail_url": "https://i.ytimg.com/vi/Q4SoBBGt_48/hqdefault.jpg"
    },
    {
      "title": "King Jay Kinda Snapped",
      "video_id": "cVeBSJ7bEmc",
      "channel_title": "Matt Steffanina",
      "description": "Learn How To Dance: http://DNCR.com ▷ INSTAGRAM: https://instagram.com/MattSteffanina ▷ TIK TOK: ...",
      "published_at": "2023-12-18T21:30:02Z",
      "thumbnail_url": "https://i.ytimg.com/vi/cVeBSJ7bEmc/hqdefault.jpg"
    }
  ]
}