{
  "fetched_at": "2026-02-22T00:38:09.690692",
  "channel_id": "UCcIXc5mJsHVYTZR1maL5l9w",
  "channel_title": "DeepLearningAI",
  "count": 10,
  "videos": [
    {
      "title": "Why Everyone Needs AI Skills",
      "video_id": "pv5g4-sEtwo",
      "channel_title": "DeepLearningAI",
      "description": "Like reading in the past, AI literacy will spread to everyone, not just engineers. Start learning AI today.",
      "published_at": "2026-02-18T13:01:27Z",
      "thumbnail_url": "https://i.ytimg.com/vi/pv5g4-sEtwo/hqdefault.jpg"
    },
    {
      "title": "Validate Your AI Idea in 48 Hours",
      "video_id": "coqS0W2AApA",
      "channel_title": "DeepLearningAI",
      "description": "You don't need weeks to test an AI idea. Use the 48-hour rule: pick one user, one job, build the smallest loop, and watch real ...",
      "published_at": "2026-02-17T13:01:06Z",
      "thumbnail_url": "https://i.ytimg.com/vi/coqS0W2AApA/hqdefault.jpg"
    },
    {
      "title": "Feeling Lost Learning AI? Watch This",
      "video_id": "nOSBnGvU_Uo",
      "channel_title": "DeepLearningAI",
      "description": "Every AI expert once Googled simple questions. Every beginner felt lost. If you're learning and trying, you belong in the AI ...",
      "published_at": "2026-02-16T13:01:32Z",
      "thumbnail_url": "https://i.ytimg.com/vi/nOSBnGvU_Uo/hqdefault.jpg"
    },
    {
      "title": "My Haircut is so Simple, It&#39;s AI-Ready 🤷‍♂️",
      "video_id": "Hwkj2CarqLc",
      "channel_title": "DeepLearningAI",
      "description": "Andrew Ng shares why his haircut might be the only one a robot could actually pull off. A fun look at the lighter side of AI ...",
      "published_at": "2026-02-15T17:00:33Z",
      "thumbnail_url": "https://i.ytimg.com/vi/Hwkj2CarqLc/hqdefault.jpg"
    },
    {
      "title": "Is EU losing the AI race?",
      "video_id": "uXPDq2zEdZk",
      "channel_title": "DeepLearningAI",
      "description": "Andrew Ng explains why you can't lead the AI revolution by trying to slow it down. A sharp critique of why heavy-handed ...",
      "published_at": "2026-02-13T14:01:26Z",
      "thumbnail_url": "https://i.ytimg.com/vi/uXPDq2zEdZk/hqdefault.jpg"
    },
    {
      "title": "Why You Need Users to Break Your AI Project",
      "video_id": "BASVwoqCPPc",
      "channel_title": "DeepLearningAI",
      "description": "Your AI idea sounds perfect on paper. Then real users show up. The fastest way to improve your AI project is to let people break it ...",
      "published_at": "2026-02-12T13:00:17Z",
      "thumbnail_url": "https://i.ytimg.com/vi/BASVwoqCPPc/hqdefault.jpg"
    },
    {
      "title": "This is why you NEED technical debt",
      "video_id": "oUampNx324w",
      "channel_title": "DeepLearningAI",
      "description": "Malte Ubl, CTO of Vercel shares the importance of technical debt. These are the kind of insights that are shared at AI Dev. Join us ...",
      "published_at": "2026-02-11T23:55:24Z",
      "thumbnail_url": "https://i.ytimg.com/vi/oUampNx324w/hqdefault.jpg"
    },
    {
      "title": "Use A2A to connect agents across different frameworks and teams",
      "video_id": "4gYm0Rp7VHc",
      "channel_title": "DeepLearningAI",
      "description": "Learn more: https://bit.ly/4anVtk6 Announcing a new short course, A2A: The Agent2Agent Protocol, built in collaboration with ...",
      "published_at": "2026-02-11T14:15:08Z",
      "thumbnail_url": "https://i.ytimg.com/vi/4gYm0Rp7VHc/hqdefault.jpg"
    },
    {
      "title": "Are Data Centers the Problem or the Scapegoat?",
      "video_id": "oeTuWr6WLrE",
      "channel_title": "DeepLearningAI",
      "description": "They power the compute we already rely on and they do it more efficiently than the alternatives.",
      "published_at": "2026-02-08T13:01:31Z",
      "thumbnail_url": "https://i.ytimg.com/vi/oeTuWr6WLrE/hqdefault.jpg"
    },
    {
      "title": "Why Your AI Team Is Slow",
      "video_id": "7zppmPvenB8",
      "channel_title": "DeepLearningAI",
      "description": "Most AI teams don't fail because of bad models. They fail because no one agrees on what “winning” means. If you try to optimize ...",
      "published_at": "2026-02-07T13:00:14Z",
      "thumbnail_url": "https://i.ytimg.com/vi/7zppmPvenB8/hqdefault.jpg"
    }
  ]
}