{
  "fetched_at": "2025-04-13T00:51:28.993263",
  "channel_id": "UCEdvpU2pFRCVqU6yIPyTpMQ",
  "channel_title": "Marshmello",
  "count": 10,
  "videos": [
    {
      "title": "it all started from somewhere #edm #music #dj #marshmello",
      "video_id": "p5BPJkkDaes",
      "channel_title": "Marshmello",
      "description": "",
      "published_at": "2025-04-11T22:00:40Z",
      "thumbnail_url": "https://i.ytimg.com/vi/p5BPJkkDaes/hqdefault.jpg"
    },
    {
      "title": "Marshmello x AR/CO - Worlds Apart (Official Performance Video)",
      "video_id": "V5XN_kDltlE",
      "channel_title": "Marshmello",
      "description": "Marshmello x AR/CO - Worlds Apart (Official Performance Video) Stream/Download: https://marshmello.ffm.to/worldsapart Official ...",
      "published_at": "2025-04-04T17:00:25Z",
      "thumbnail_url": "https://i.ytimg.com/vi/V5XN_kDltlE/hqdefault.jpg"
    },
    {
      "title": "Marshmello x AR/CO - Worlds Apart (Official Visualizer)",
      "video_id": "e5-fzHNap4M",
      "channel_title": "Marshmello",
      "description": "Marshmello x AR/CO - Worlds Apart (Official Visualizer) Stream/Download: https://marshmello.ffm.to/worldsapart Official ...",
      "published_at": "2025-03-28T03:46:23Z",
      "thumbnail_url": "https://i.ytimg.com/vi/e5-fzHNap4M/hqdefault.jpg"
    },
    {
      "title": "Marshmello x TRICKSTAR x Lil Jon - Bad Boys (Dr. Apollo Remix)",
      "video_id": "yrx-jD6VWrg",
      "channel_title": "Marshmello",
      "description": "Marshmello x TRICKSTAR x Lil Jon - Bad Boys (Dr. Apollo Remix) Stream/Download: https://marshmello.ffm.to/therootsremixes ...",
      "published_at": "2025-03-07T05:00:52Z",
      "thumbnail_url": "https://i.ytimg.com/vi/yrx-jD6VWrg/hqdefault.jpg"
    },
    {
      "title": "Marshmello - Just Can&#39;t Stop (SPACECHANGER x Anger Issues Remix)",
      "video_id": "_3DD5QIZYHs",
      "channel_title": "Marshmello",
      "description": "Marshmello - Just Can't Stop (SPACECHANGER x Anger Issues Remix) stream/download: ...",
      "published_at": "2025-03-07T05:00:38Z",
      "thumbnail_url": "https://i.ytimg.com/vi/_3DD5QIZYHs/hqdefault.jpg"
    },
    {
      "title": "Marshmello - Just Can&#39;t Stop (Pryzms Remix)",
      "video_id": "6j-PZTxYlbQ",
      "channel_title": "Marshmello",
      "description": "Marshmello - Just Can't Stop (Pryzms Remix) stream/download: https://marshmello.ffm.to/therootsremixes stream/download \"The ...",
      "published_at": "2025-03-07T05:00:05Z",
      "thumbnail_url": "https://i.ytimg.com/vi/6j-PZTxYlbQ/hqdefault.jpg"
    },
    {
      "title": "Marshmello - Just Can&#39;t Stop (SKAN Remix)",
      "video_id": "O43_rqRFhkM",
      "channel_title": "Marshmello",
      "description": "Marshmello - Just Can't Stop (SKAN Remix) stream/download: https://marshmello.ffm.to/therootsremixes stream/download \"The ...",
      "published_at": "2025-03-07T05:00:21Z",
      "thumbnail_url": "https://i.ytimg.com/vi/O43_rqRFhkM/hqdefault.jpg"
    },
    {
      "title": "Marshmello - Da Da Da (The Arp Song) (Hekler Remix)",
      "video_id": "EOY-cwR0018",
      "channel_title": "Marshmello",
      "description": "Marshmello - Da Da Da (The Arp Song) (Hekler Remix) stream/download: https://marshmello.ffm.to/therootsremixes ...",
      "published_at": "2025-03-07T05:00:12Z",
      "thumbnail_url": "https://i.ytimg.com/vi/EOY-cwR0018/hqdefault.jpg"
    },
    {
      "title": "Marshmello x Hamdi - Fired Up (MUNK Remix)",
      "video_id": "f6gp3rE2eyQ",
      "channel_title": "Marshmello",
      "description": "Marshmello x Hamdi - Fired Up (MUNK Remix) Stream/Download: https://marshmello.ffm.to/therootsremixes Official Marshmello ...",
      "published_at": "2025-03-07T05:00:41Z",
      "thumbnail_url": "https://i.ytimg.com/vi/f6gp3rE2eyQ/hqdefault.jpg"
    },
    {
      "title": "Marshmello x Viperactive - In The Cut (VIP)",
      "video_id": "OqaKdpG4MZc",
      "channel_title": "Marshmello",
      "description": "Marshmello x Viperactive - In The Cut (VIP) Stream/Download: https://marshmello.ffm.to/therootsremixes Stream/Download The ...",
      "published_at": "2025-03-07T04:45:02Z",
      "thumbnail_url": "https://i.ytimg.com/vi/OqaKdpG4MZc/hqdefault.jpg"
    }
  ]
}