{
  "fetched_at": "2025-12-14T00:33:01.410708",
  "channel_id": "UCh2dnrLCNHDS2IV9I2R58Pw",
  "channel_title": "Hazegrayart",
  "count": 10,
  "videos": [
    {
      "title": "Buran Space Shuttle  MIR-2 Space Station",
      "video_id": "MfkcoX0GEAc",
      "channel_title": "Hazegrayart",
      "description": "Buran was the Soviet Union's reusable space shuttle orbiter, developed in the 1970s–1980s as part of the Energia–Buran ...",
      "published_at": "2025-12-11T18:00:41Z",
      "thumbnail_url": "https://i.ytimg.com/vi/MfkcoX0GEAc/hqdefault.jpg"
    },
    {
      "title": "Dual Keel Space Station Freedom  #spacestation #iss #nasa",
      "video_id": "h3vlGpqng3E",
      "channel_title": "Hazegrayart",
      "description": "President Reagan's key space station speech was in his 1984 State of the Union address, where he directed NASA to develop a ...",
      "published_at": "2025-12-10T17:01:16Z",
      "thumbnail_url": "https://i.ytimg.com/vi/h3vlGpqng3E/hqdefault.jpg"
    },
    {
      "title": "Space Station Freedom  #spacestation #iss #nasa",
      "video_id": "QDaup6R8ztg",
      "channel_title": "Hazegrayart",
      "description": "President Reagan's key space station speech was in his 1984 State of the Union address, where he directed NASA to develop a ...",
      "published_at": "2025-12-09T13:01:01Z",
      "thumbnail_url": "https://i.ytimg.com/vi/QDaup6R8ztg/hqdefault.jpg"
    },
    {
      "title": "Space Shuttle Reentry",
      "video_id": "62lHjreVhwU",
      "channel_title": "Hazegrayart",
      "description": "A Space Shuttle Concept The experts at OKB-1, pioneers behind the Soyuz capsule, were decidedly unimpressed with the ...",
      "published_at": "2025-12-07T12:05:25Z",
      "thumbnail_url": "https://i.ytimg.com/vi/62lHjreVhwU/hqdefault.jpg"
    },
    {
      "title": "President Reagan directs NASA to build  Space Station Freedom",
      "video_id": "D5XZEkD2V9U",
      "channel_title": "Hazegrayart",
      "description": "President Reagan's key space station speech was in his 1984 State of the Union address, where he directed NASA to develop a ...",
      "published_at": "2025-12-07T10:28:23Z",
      "thumbnail_url": "https://i.ytimg.com/vi/D5XZEkD2V9U/hqdefault.jpg"
    },
    {
      "title": "That Time Apollo 12 Got Struck by Lightning, Twice",
      "video_id": "_D0aeR0IB7s",
      "channel_title": "Hazegrayart",
      "description": "rocket #apollo #saturnv On November 14, 1969, at 11:22 a.m. ET, Apollo 12 with NASA astronauts Charles \"Pete\" Conrad, Alan ...",
      "published_at": "2025-11-14T20:22:00Z",
      "thumbnail_url": "https://i.ytimg.com/vi/_D0aeR0IB7s/hqdefault.jpg"
    },
    {
      "title": "Autonomous Spaceport Drone Ship Landing #rocketlab  #rocket #automobile",
      "video_id": "wo1oLquMnBM",
      "channel_title": "Hazegrayart",
      "description": "An autonomous spaceport drone ship (ASDS) is an ocean-going vessel derived from a deck barge, outfitted with station-keeping ...",
      "published_at": "2025-11-06T01:44:15Z",
      "thumbnail_url": "https://i.ytimg.com/vi/wo1oLquMnBM/hqdefault.jpg"
    },
    {
      "title": "DARPA Hammerhead  Fuel Tank",
      "video_id": "0aN63tMjz94",
      "channel_title": "Hazegrayart",
      "description": "DARPA studied modifying the current external tank design to be able to carry low-density payloads in a 25 or 35 ft (7.6 or 10.6 m) ...",
      "published_at": "2025-11-02T13:00:04Z",
      "thumbnail_url": "https://i.ytimg.com/vi/0aN63tMjz94/hqdefault.jpg"
    },
    {
      "title": "Launching Rockets from Aircraft Carries",
      "video_id": "iEO5TVAVPtk",
      "channel_title": "Hazegrayart",
      "description": "Operation Sandy was the codename for the post-World War II launch of a captured V-2 rocket from the deck of the United States ...",
      "published_at": "2025-10-25T19:10:15Z",
      "thumbnail_url": "https://i.ytimg.com/vi/iEO5TVAVPtk/hqdefault.jpg"
    },
    {
      "title": "Buran Space Shuttle",
      "video_id": "0fnsC-FxF8Y",
      "channel_title": "Hazegrayart",
      "description": "The Buran (Russian for \"snowstorm\") was the Soviet Union's reusable space shuttle, developed as a direct response to the ...",
      "published_at": "2025-10-23T10:27:35Z",
      "thumbnail_url": "https://i.ytimg.com/vi/0fnsC-FxF8Y/hqdefault.jpg"
    }
  ]
}