{
  "fetched_at": "2025-05-18T00:30:03.860972",
  "channel_id": "UCK8sQmJBp8GCxrOtXWBpyEA",
  "channel_title": "Google",
  "count": 3,
  "videos": [
    {
      "title": "Stuck on a problem? Use AI Overviews in Search to get a step-by-step explanation",
      "video_id": "TiVBvgIxsQw",
      "channel_title": "Google",
      "description": "Subscribe to our Channel: https://www.youtube.com/google Find us on X: https://twitter.com/google Watch us on TikTok: ...",
      "published_at": "2025-05-16T18:32:09Z",
      "thumbnail_url": "https://i.ytimg.com/vi/TiVBvgIxsQw/hqdefault.jpg"
    },
    {
      "title": "Ready, set, I/O",
      "video_id": "QOIDdIzX9uY",
      "channel_title": "Google",
      "description": "It's time to I/O! Tune in on May 20 at 10am PT to learn the latest news, announcements, and AI updates from Google. Be the first to ...",
      "published_at": "2025-05-08T16:19:37Z",
      "thumbnail_url": "https://i.ytimg.com/vi/QOIDdIzX9uY/hqdefault.jpg"
    },
    {
      "title": "Google I/O &#39;25 Keynote - American Sign Language",
      "video_id": "0BLsd7HfU9w",
      "channel_title": "Google",
      "description": "It's time to I/O! Tune in to learn the latest news, announcements, and AI updates from Google. Click “Notify me” to receive a ...",
      "published_at": "2025-03-11T17:45:09Z",
      "thumbnail_url": "https://i.ytimg.com/vi/0BLsd7HfU9w/hqdefault_live.jpg"
    }
  ]
}