{
  "fetched_at": "2026-03-29T00:44:05.915894",
  "channel_id": "UCKSVUHI9rbbkXhvAXK-2uxA",
  "channel_title": "Supercar Blondie",
  "count": 10,
  "videos": [
    {
      "title": "Boat vs Crane! 🤯",
      "video_id": "Q-VwNMrJh4c",
      "channel_title": "Supercar Blondie",
      "description": "Huge thanks to @rafnarmaritime for providing us with a look at their self-righting boat! Check out more from them below!",
      "published_at": "2026-03-28T13:00:00Z",
      "thumbnail_url": "https://i.ytimg.com/vi/Q-VwNMrJh4c/hqdefault.jpg"
    },
    {
      "title": "Offroad Maybach! 🤯",
      "video_id": "Xyw7SuYzxwA",
      "channel_title": "Supercar Blondie",
      "description": "To buy or sell the rarest cars on the planet, head to our auction platform SBX Cars: https://go.sbxcars.com/SBXAuctions You can ...",
      "published_at": "2026-03-28T11:00:00Z",
      "thumbnail_url": "https://i.ytimg.com/vi/Xyw7SuYzxwA/hqdefault.jpg"
    },
    {
      "title": "A snow plow for crabs! 🦀",
      "video_id": "j-EFdHmJldQ",
      "channel_title": "Supercar Blondie",
      "description": "Huge thanks to chrisbrayphotography for providing us with a look at their crab plow! Check out more from them below!",
      "published_at": "2026-03-27T13:00:00Z",
      "thumbnail_url": "https://i.ytimg.com/vi/j-EFdHmJldQ/hqdefault.jpg"
    },
    {
      "title": "Police Car For The Desert! 🌵",
      "video_id": "teIimrr701g",
      "channel_title": "Supercar Blondie",
      "description": "To buy or sell the rarest cars on the planet, head to our auction platform SBX Cars: https://go.sbxcars.com/SBXAuctions You can ...",
      "published_at": "2026-03-27T11:00:00Z",
      "thumbnail_url": "https://i.ytimg.com/vi/teIimrr701g/hqdefault.jpg"
    },
    {
      "title": "Immersive MotoGP Simulator! 🏍️",
      "video_id": "tiBpx1OQBVQ",
      "channel_title": "Supercar Blondie",
      "description": "Huge thanks to emiliadobrev for providing us with a look at their simulator skills! Check out more from them below!",
      "published_at": "2026-03-26T13:00:00Z",
      "thumbnail_url": "https://i.ytimg.com/vi/tiBpx1OQBVQ/hqdefault.jpg"
    },
    {
      "title": "Crazy quirks Of The Alfa Romeo Stradale! 🤯",
      "video_id": "ytNOJH917bs",
      "channel_title": "Supercar Blondie",
      "description": "To buy or sell the rarest cars on the planet, head to our auction platform SBX Cars: https://go.sbxcars.com/SBXAuctions You can ...",
      "published_at": "2026-03-26T11:00:00Z",
      "thumbnail_url": "https://i.ytimg.com/vi/ytNOJH917bs/hqdefault.jpg"
    },
    {
      "title": "Filling A Vehicle With Smoke! 😱",
      "video_id": "YPUtFtASTTw",
      "channel_title": "Supercar Blondie",
      "description": "Huge thanks to luxwash_moldova for providing us with a look at their car smoke! Check out more from them below!",
      "published_at": "2026-03-25T13:00:00Z",
      "thumbnail_url": "https://i.ytimg.com/vi/YPUtFtASTTw/hqdefault.jpg"
    },
    {
      "title": "Lost 1930s supercar, finally brought to life! 🤯",
      "video_id": "gNusmeRpZtQ",
      "channel_title": "Supercar Blondie",
      "description": "To buy or sell the rarest cars on the planet, head to our auction platform SBX Cars: https://go.sbxcars.com/SBXAuctions You can ...",
      "published_at": "2026-03-25T11:00:00Z",
      "thumbnail_url": "https://i.ytimg.com/vi/gNusmeRpZtQ/hqdefault.jpg"
    },
    {
      "title": "Motorized Pole Climber! 🤯",
      "video_id": "cTz0BQu0EKw",
      "channel_title": "Supercar Blondie",
      "description": "Huge thanks to farmerszone_fzmart for providing us with a look at their motorized pole climber! Check out more from them below!",
      "published_at": "2026-03-24T13:00:00Z",
      "thumbnail_url": "https://i.ytimg.com/vi/cTz0BQu0EKw/hqdefault.jpg"
    },
    {
      "title": "This car is Asymmetrical!  🤯",
      "video_id": "Mab9rnA4Iio",
      "channel_title": "Supercar Blondie",
      "description": "To buy or sell the rarest cars on the planet, head to our auction platform SBX Cars: https://go.sbxcars.com/SBXAuctions You can ...",
      "published_at": "2026-03-24T11:00:00Z",
      "thumbnail_url": "https://i.ytimg.com/vi/Mab9rnA4Iio/hqdefault.jpg"
    }
  ]
}