{
  "fetched_at": "2025-08-31T00:29:16.381546",
  "channel_id": "UCKSVUHI9rbbkXhvAXK-2uxA",
  "channel_title": "Supercar Blondie",
  "count": 10,
  "videos": [
    {
      "title": "Colorful Car Wash! 🎨 #paint #carwash #cleaning",
      "video_id": "sGdN42LRaZ0",
      "channel_title": "Supercar Blondie",
      "description": "To buy or sell the rarest cars on the planet, head to our auction platform SBX Cars: https://go.sbxcars.com/SBXAuctions You can ...",
      "published_at": "2025-08-30T15:01:29Z",
      "thumbnail_url": "https://i.ytimg.com/vi/sGdN42LRaZ0/hqdefault.jpg"
    },
    {
      "title": "1968 GT500 Shelby Fastback! 😍 ​⁠@sbxcars  #cars #mustang #movies",
      "video_id": "PPnyRhJMd5Q",
      "channel_title": "Supercar Blondie",
      "description": "To buy or sell the rarest cars on the planet, head to our auction platform SBX Cars: https://go.sbxcars.com/SBXAuctions You can ...",
      "published_at": "2025-08-30T12:00:55Z",
      "thumbnail_url": "https://i.ytimg.com/vi/PPnyRhJMd5Q/hqdefault.jpg"
    },
    {
      "title": "Drivers vs. Wet Surfaces! 💦 #cars #water #drift",
      "video_id": "he-bffUQHc0",
      "channel_title": "Supercar Blondie",
      "description": "To buy or sell the rarest cars on the planet, head to our auction platform SBX Cars: https://go.sbxcars.com/SBXAuctions You can ...",
      "published_at": "2025-08-30T09:01:03Z",
      "thumbnail_url": "https://i.ytimg.com/vi/he-bffUQHc0/hqdefault.jpg"
    },
    {
      "title": "Kid&#39;s Car With A Real Engine! 🔥 #cars #toycar #toys",
      "video_id": "ZeI3jWCPk5o",
      "channel_title": "Supercar Blondie",
      "description": "To buy or sell the rarest cars on the planet, head to our auction platform SBX Cars: https://go.sbxcars.com/SBXAuctions You can ...",
      "published_at": "2025-08-29T15:01:12Z",
      "thumbnail_url": "https://i.ytimg.com/vi/ZeI3jWCPk5o/hqdefault.jpg"
    },
    {
      "title": "Rolls-Royce Cullinan Series II 🔥 ​⁠@sbxcars #rollsroyce #cars #luxury",
      "video_id": "R02h-JYhqvo",
      "channel_title": "Supercar Blondie",
      "description": "To buy or sell the rarest cars on the planet, head to our auction platform SBX Cars: https://go.sbxcars.com/SBXAuctions You can ...",
      "published_at": "2025-08-29T12:01:01Z",
      "thumbnail_url": "https://i.ytimg.com/vi/R02h-JYhqvo/hqdefault.jpg"
    },
    {
      "title": "Cutting Through A Porsche! 😱 #porsche #supercars #cars",
      "video_id": "VjXhr1tGKSY",
      "channel_title": "Supercar Blondie",
      "description": "To buy or sell the rarest cars on the planet, head to our auction platform SBX Cars: https://go.sbxcars.com/SBXAuctions You can ...",
      "published_at": "2025-08-29T09:00:48Z",
      "thumbnail_url": "https://i.ytimg.com/vi/VjXhr1tGKSY/hqdefault.jpg"
    },
    {
      "title": "An Electric Bike Car?! 🤯 #cars #bikes #electric",
      "video_id": "LG8CusmrOKg",
      "channel_title": "Supercar Blondie",
      "description": "To buy or sell the rarest cars on the planet, head to our auction platform SBX Cars: https://go.sbxcars.com/SBXAuctions You can ...",
      "published_at": "2025-08-28T15:00:39Z",
      "thumbnail_url": "https://i.ytimg.com/vi/LG8CusmrOKg/hqdefault.jpg"
    },
    {
      "title": "Huge Scalextrics Track 🏎️ #scalextrics #racing #cars",
      "video_id": "9DozcMdQLaU",
      "channel_title": "Supercar Blondie",
      "description": "To buy or sell the rarest cars on the planet, head to our auction platform SBX Cars: https://go.sbxcars.com/SBXAuctions You can ...",
      "published_at": "2025-08-28T12:00:25Z",
      "thumbnail_url": "https://i.ytimg.com/vi/9DozcMdQLaU/hqdefault.jpg"
    },
    {
      "title": "Super Rare Aston Martin! 😳 ​⁠@sbxcars  #astonmartin #mansory #supercars",
      "video_id": "oc7jhRqjW1g",
      "channel_title": "Supercar Blondie",
      "description": "To buy or sell the rarest cars on the planet, head to our auction platform SBX Cars: https://go.sbxcars.com/SBXAuctions You can ...",
      "published_at": "2025-08-28T09:01:22Z",
      "thumbnail_url": "https://i.ytimg.com/vi/oc7jhRqjW1g/hqdefault.jpg"
    },
    {
      "title": "$100 Rolls Royce vs $20,000,000 Rolls Royce",
      "video_id": "xcLaUByqzMk",
      "channel_title": "Supercar Blondie",
      "description": "We travelled across Europe in search of the cheapest to most expensive Rolls Royces we could find. From a beat up $100 Rolls ...",
      "published_at": "2025-08-27T16:01:42Z",
      "thumbnail_url": "https://i.ytimg.com/vi/xcLaUByqzMk/hqdefault.jpg"
    }
  ]
}