{
  "fetched_at": "2026-04-19T00:48:15.176981",
  "channel_id": "UCLA_DiR1FfKNvjuUpBHmylQ",
  "channel_title": "NASA",
  "count": 10,
  "videos": [
    {
      "title": "Welcome Home, Artemis II (Official NASA Recap)",
      "video_id": "AYSE6QLigik",
      "channel_title": "NASA",
      "description": "Our Artemis II mission concluded its historic flight around the Moon on April 10, 2026. Among its many milestones, Artemis II ...",
      "published_at": "2026-04-17T19:48:19Z",
      "thumbnail_url": "https://i.ytimg.com/vi/AYSE6QLigik/hqdefault.jpg"
    },
    {
      "title": "Moonbound Episode 2 | For All Humanity",
      "video_id": "ttiLcMUQq80",
      "channel_title": "NASA",
      "description": "With the Artemis II mission, four astronauts transitioned from years of training to mission-ready reality. The second episode of our ...",
      "published_at": "2026-04-17T19:06:55Z",
      "thumbnail_url": "https://i.ytimg.com/vi/ttiLcMUQq80/hqdefault.jpg"
    },
    {
      "title": "Moonbound Episode 1 | Charting the Course",
      "video_id": "bfw4G59j9uw",
      "channel_title": "NASA",
      "description": "Artemis II and its test flight around the Moon transformed plans and preparation into execution and exploration. The first episode of ...",
      "published_at": "2026-04-17T17:28:01Z",
      "thumbnail_url": "https://i.ytimg.com/vi/bfw4G59j9uw/hqdefault.jpg"
    },
    {
      "title": "Official Static Feed: NASA&#39;s Mobile Launcher on the Move (April 17, 2026)",
      "video_id": "zgnmbCWYixM",
      "channel_title": "NASA",
      "description": "NASA's mobile launcher is on the move as teams prepare for the upcoming Artemis III mission. The massive structure will begin to ...",
      "published_at": "2026-04-17T16:16:56Z",
      "thumbnail_url": "https://i.ytimg.com/vi/zgnmbCWYixM/hqdefault.jpg"
    },
    {
      "title": "NASA Force: The Next Era of NASA Starts with You",
      "video_id": "hfoHFnGuVCw",
      "channel_title": "NASA",
      "description": "NASA Administrator Jared Isaacman introduces NASA Force, a new initiative to bring highly skilled engineers, technologists, and ...",
      "published_at": "2026-04-17T15:21:34Z",
      "thumbnail_url": "https://i.ytimg.com/vi/hfoHFnGuVCw/hqdefault.jpg"
    },
    {
      "title": "Reflections from the Artemis II Crew",
      "video_id": "WhNzhnXO16c",
      "channel_title": "NASA",
      "description": "\"We've done this together. We took your hearts with us, and your hearts lifted our hearts.\" - Christina Koch⁣ ⁣ In a news ...",
      "published_at": "2026-04-16T21:54:39Z",
      "thumbnail_url": "https://i.ytimg.com/vi/WhNzhnXO16c/hqdefault.jpg"
    },
    {
      "title": "Official Static Feed: NASA&#39;s Mobile Launcher on the Move (April 16, 2026)",
      "video_id": "KQ3YB0woUbY",
      "channel_title": "NASA",
      "description": "NASA's mobile launcher is on the move as teams prepare for the upcoming Artemis III mission. The massive structure will begin to ...",
      "published_at": "2026-04-16T20:17:46Z",
      "thumbnail_url": "https://i.ytimg.com/vi/KQ3YB0woUbY/hqdefault.jpg"
    },
    {
      "title": "NASA&#39;s Artemis II News Conference with Moon Astronauts (April 16, 2026)",
      "video_id": "_43Ei9eQVww",
      "channel_title": "NASA",
      "description": "Live from NASA's Johnson Space Center in Houston, join the astronauts of Artemis II as they discuss their mission around the ...",
      "published_at": "2026-04-16T19:33:54Z",
      "thumbnail_url": "https://i.ytimg.com/vi/_43Ei9eQVww/hqdefault.jpg"
    },
    {
      "title": "NASA News Conference: Nancy Grace Roman Space Telescope is Complete (April 21, 2026)",
      "video_id": "XX4f6dOoi08",
      "channel_title": "NASA",
      "description": "Our new flagship telescope is fully assembled. Come find out what it will discover. We're hosting a news conference at NASA's ...",
      "published_at": "2026-04-15T22:05:40Z",
      "thumbnail_url": "https://i.ytimg.com/vi/XX4f6dOoi08/hqdefault_live.jpg"
    },
    {
      "title": "NASA&#39;s Northrop Grumman Commercial Resupply Services 24 Rendezvous &amp; Capture",
      "video_id": "EnNGVjOy33U",
      "channel_title": "NASA",
      "description": "Northrop Grumman's Cygnus XL cargo spacecraft arrives at the International Space Station, delivering supplies, new research, ...",
      "published_at": "2026-04-13T17:33:04Z",
      "thumbnail_url": "https://i.ytimg.com/vi/EnNGVjOy33U/hqdefault.jpg"
    }
  ]
}