{
  "fetched_at": "2025-08-03T00:34:12.332348",
  "channel_id": "UCnyJbOnQSqZ6WrTv32mX4Dg",
  "channel_title": "Brutal Bikes",
  "count": 10,
  "videos": [
    {
      "title": "WE WILL RIDE - TILL WE DIE (feat. FlicksbyJames Revrozell, ImKay &amp; Steve Stacey)",
      "video_id": "GXYbwPmokBc",
      "channel_title": "Brutal Bikes",
      "description": "Shop ▻ http://brutalbikes.shop Instagram ▻ https://www.instagram.com/brutal_bikes Show some love to ▻ FlicksByJames ...",
      "published_at": "2025-08-01T13:00:35Z",
      "thumbnail_url": "https://i.ytimg.com/vi/GXYbwPmokBc/hqdefault.jpg"
    },
    {
      "title": "Superbike Invasion - City takeover (feat. FlicksbyJames Revrozell, ImKay &amp; Steve Stacey)",
      "video_id": "5APUkiplwSQ",
      "channel_title": "Brutal Bikes",
      "description": "Shop ▻ http://brutalbikes.shop Instagram ▻ https://www.instagram.com/brutal_bikes Show some love to ▻ FlicksByJames ...",
      "published_at": "2025-07-27T13:05:05Z",
      "thumbnail_url": "https://i.ytimg.com/vi/5APUkiplwSQ/hqdefault.jpg"
    },
    {
      "title": "Hey mama - Panigale V4S (feat.ThirdEye, ImKay &amp; Steve Stacey)",
      "video_id": "r-gNI8P90ZI",
      "channel_title": "Brutal Bikes",
      "description": "Shop ▻ http://brutalbikes.shop Instagram ▻ https://www.instagram.com/brutal_bikes Show some love to ▻ ThirdEyeProductions ...",
      "published_at": "2025-07-15T13:01:48Z",
      "thumbnail_url": "https://i.ytimg.com/vi/r-gNI8P90ZI/hqdefault.jpg"
    },
    {
      "title": "PURE BEAST - BMW S1000RR &amp; M1000RR (feat. InfamouzCulture)",
      "video_id": "2OS7-9YssT4",
      "channel_title": "Brutal Bikes",
      "description": "Shop ▻ http://brutalbikes.shop Instagram ▻ https://www.instagram.com/brutal_bikes Show some love to ...",
      "published_at": "2025-07-09T13:00:04Z",
      "thumbnail_url": "https://i.ytimg.com/vi/2OS7-9YssT4/hqdefault.jpg"
    },
    {
      "title": "WHEN THE SUN GOES DOWN - BMW S1000RR (feat. ThirdEye, Motorbikemedia, InfamouzCulture )",
      "video_id": "yfRyyEvWK3s",
      "channel_title": "Brutal Bikes",
      "description": "Shop ▻ http://brutalbikes.shop Instagram ▻ https://www.instagram.com/brutal_bikes Show some love to ▻ ThirdEyeProductions ...",
      "published_at": "2025-07-03T15:16:57Z",
      "thumbnail_url": "https://i.ytimg.com/vi/yfRyyEvWK3s/hqdefault.jpg"
    },
    {
      "title": "NO MERCY - Panigale V4SP (feat. Weir Productions Evil Media)",
      "video_id": "UCAti6EAHFQ",
      "channel_title": "Brutal Bikes",
      "description": "Shop ▻ http://brutalbikes.shop Instagram ▻ https://www.instagram.com/brutal_bikes Show some love to ▻ Harrison Weir ...",
      "published_at": "2025-06-25T20:54:51Z",
      "thumbnail_url": "https://i.ytimg.com/vi/UCAti6EAHFQ/hqdefault.jpg"
    },
    {
      "title": "UNDERWORLD - Kawasaki H2R (feat. ImKay &amp; Steve Stacey)",
      "video_id": "GcTEOJSWyo4",
      "channel_title": "Brutal Bikes",
      "description": "Shop ▻ http://brutalbikes.shop Instagram ▻ https://www.instagram.com/brutal_bikes Show some love to ▻ Steve Stacey ...",
      "published_at": "2025-06-11T13:00:27Z",
      "thumbnail_url": "https://i.ytimg.com/vi/GcTEOJSWyo4/hqdefault.jpg"
    },
    {
      "title": "DIE WITH MEMORIES - NOT DREAMS / Hoodie /// brutal-bikes.com #shorts",
      "video_id": "K7MbkePS9zs",
      "channel_title": "Brutal Bikes",
      "description": "Shop ▻ http://brutalbikes.shop Instagram ▻ https://www.instagram.com/brutal_bikes Get Alerts! Click the Notification Bell next ...",
      "published_at": "2025-05-19T22:00:33Z",
      "thumbnail_url": "https://i.ytimg.com/vi/K7MbkePS9zs/hqdefault.jpg"
    },
    {
      "title": "LOOK MOM - I CAN FLY / Hoodie /// brutal-bikes.com #shorts",
      "video_id": "VRkG80TKZnE",
      "channel_title": "Brutal Bikes",
      "description": "Shop ▻ http://brutalbikes.shop Instagram ▻ https://www.instagram.com/brutal_bikes Get Alerts! Click the Notification Bell next ...",
      "published_at": "2025-05-19T13:00:56Z",
      "thumbnail_url": "https://i.ytimg.com/vi/VRkG80TKZnE/hqdefault.jpg"
    },
    {
      "title": "AIRPLANE MODE - S1000RR / SUPERBIKES (feat. InfamouzCulture)",
      "video_id": "-cT_-qIl3kA",
      "channel_title": "Brutal Bikes",
      "description": "Video Production ▻ https://www.instagram.com/fullrez.arw/ Shop ▻ http://brutalbikes.shop Instagram ...",
      "published_at": "2025-05-18T13:00:01Z",
      "thumbnail_url": "https://i.ytimg.com/vi/-cT_-qIl3kA/hqdefault.jpg"
    }
  ]
}