{
  "fetched_at": "2025-09-14T00:28:35.780736",
  "channel_id": "UCqS6lrGPIPRfFJePMBX5fPA",
  "channel_title": "Drex Lee",
  "count": 10,
  "videos": [
    {
      "title": "Epic 360 drone Drive off 1 Shot 💥 see Results ‼️ #insta360 #automobile #drexlee",
      "video_id": "R3-QFur_2sM",
      "channel_title": "Drex Lee",
      "description": "",
      "published_at": "2025-09-12T14:00:46Z",
      "thumbnail_url": "https://i.ytimg.com/vi/R3-QFur_2sM/hqdefault.jpg"
    },
    {
      "title": "Try this epic Night drive shot idea 💥 see Results ‼️",
      "video_id": "UKv2LTzHUik",
      "channel_title": "Drex Lee",
      "description": "",
      "published_at": "2025-09-11T14:00:54Z",
      "thumbnail_url": "https://i.ytimg.com/vi/UKv2LTzHUik/hqdefault.jpg"
    },
    {
      "title": "Try this Epic Benz Transition Shot💥 Save for later ‼️ #drexlee",
      "video_id": "N09auTngq0Y",
      "channel_title": "Drex Lee",
      "description": "",
      "published_at": "2025-09-10T14:00:41Z",
      "thumbnail_url": "https://i.ytimg.com/vi/N09auTngq0Y/hqdefault.jpg"
    },
    {
      "title": "Epic Supra 1 Shot 💥 see Results ‼️",
      "video_id": "ifvYUj7ORzs",
      "channel_title": "Drex Lee",
      "description": "",
      "published_at": "2025-09-05T14:01:17Z",
      "thumbnail_url": "https://i.ytimg.com/vi/ifvYUj7ORzs/hqdefault.jpg"
    },
    {
      "title": "Try this creative lighting trick 💥 see Results ‼️ #drexlee",
      "video_id": "3z1_IYGAqzw",
      "channel_title": "Drex Lee",
      "description": "",
      "published_at": "2025-09-02T00:04:33Z",
      "thumbnail_url": "https://i.ytimg.com/vi/3z1_IYGAqzw/hqdefault.jpg"
    },
    {
      "title": "Try this Selfie Driving Shot idea💥 see Results ‼️",
      "video_id": "xIBRSCfmwlU",
      "channel_title": "Drex Lee",
      "description": "Shorts #viralshorts #automobile #cinematic.",
      "published_at": "2025-08-23T10:49:30Z",
      "thumbnail_url": "https://i.ytimg.com/vi/xIBRSCfmwlU/hqdefault.jpg"
    },
    {
      "title": "Try this creative drive video idea 💥 Send to a friend 🔥",
      "video_id": "pAjyllF77c8",
      "channel_title": "Drex Lee",
      "description": "",
      "published_at": "2025-08-21T18:10:23Z",
      "thumbnail_url": "https://i.ytimg.com/vi/pAjyllF77c8/hqdefault.jpg"
    },
    {
      "title": "Filming car audio 💥 captured with Hollyland Lark Max 2 🚀 #Hollyland #HollylandMic #LARKMAX2",
      "video_id": "wrKEG7ZTnG8",
      "channel_title": "Drex Lee",
      "description": "",
      "published_at": "2025-08-18T14:01:26Z",
      "thumbnail_url": "https://i.ytimg.com/vi/wrKEG7ZTnG8/hqdefault.jpg"
    },
    {
      "title": "Epic 1 Shot cinematic💥 see Results ‼️with Ashley Vee 🔥 #drexlee #shorts",
      "video_id": "-X8Unm0LIas",
      "channel_title": "Drex Lee",
      "description": "edit #creative #viralshorts #supercars #mercedes.",
      "published_at": "2025-08-14T14:30:01Z",
      "thumbnail_url": "https://i.ytimg.com/vi/-X8Unm0LIas/hqdefault.jpg"
    },
    {
      "title": "Mind-blowing 200 Megapixel Camera on the Galaxy Z Fold7 🤯 See results! #SamsungPartner #TeamGalaxy",
      "video_id": "K3TQtwqjaj8",
      "channel_title": "Drex Lee",
      "description": "GalaxyZFold7 #withGalaxy #ExploreGalaxy @SamsungMobileUSA.",
      "published_at": "2025-08-13T00:30:56Z",
      "thumbnail_url": "https://i.ytimg.com/vi/K3TQtwqjaj8/hqdefault.jpg"
    }
  ]
}