{
  "fetched_at": "2025-06-29T00:32:02.318399",
  "channel_id": "UCREFp3D_n8JfcDonlm7Mpyw",
  "channel_title": "Programiz",
  "count": 10,
  "videos": [
    {
      "title": "Introducing Code Visualizer: Learn to Code with Visuals",
      "video_id": "c6nr9T7aoP0",
      "channel_title": "Programiz",
      "description": "Ever written code that should work... but doesn't? With Code Visualizer, you can watch your code run line by line and see exactly ...",
      "published_at": "2025-06-26T12:15:08Z",
      "thumbnail_url": "https://i.ytimg.com/vi/c6nr9T7aoP0/hqdefault.jpg"
    },
    {
      "title": "Why use Ask Programiz instead of AI? #shorts",
      "video_id": "PBm5d07HY_k",
      "channel_title": "Programiz",
      "description": "Stuck on a concept while learning to code? You're not alone — and you don't have to figure it out alone either. With Ask ...",
      "published_at": "2025-06-12T12:15:02Z",
      "thumbnail_url": "https://i.ytimg.com/vi/PBm5d07HY_k/hqdefault.jpg"
    },
    {
      "title": "Tired of Errors? Start Coding in Seconds! #shorts",
      "video_id": "2GfhUs1g3kI",
      "channel_title": "Programiz",
      "description": "Struggling to get started with coding? Let's fix that! You've probably been there — you're ready to learn to code, open your laptop, ...",
      "published_at": "2025-05-22T11:15:00Z",
      "thumbnail_url": "https://i.ytimg.com/vi/2GfhUs1g3kI/hqdefault.jpg"
    },
    {
      "title": "Stuck in Tutorial Hell? (Do this instead) #shorts",
      "video_id": "rczNFVfIcbs",
      "channel_title": "Programiz",
      "description": "\"I watched hours of coding tutorials and still felt lost.\" If that sounds familiar, you're not alone. Most courses teach you to watch, not ...",
      "published_at": "2025-05-07T12:15:17Z",
      "thumbnail_url": "https://i.ytimg.com/vi/rczNFVfIcbs/hqdefault.jpg"
    },
    {
      "title": "&quot;I passed my C++ exam with Programiz PRO.” -  Landon | Learner story",
      "video_id": "cwp0JmX8HoA",
      "channel_title": "Programiz",
      "description": "I was lucky to come across Programiz PRO because it instantly changed my experience of learning to code. Programiz PRO has ...",
      "published_at": "2025-04-30T11:15:10Z",
      "thumbnail_url": "https://i.ytimg.com/vi/cwp0JmX8HoA/hqdefault.jpg"
    },
    {
      "title": "Is learning to code worth it in 2025? #shorts",
      "video_id": "WTfn7dIddt8",
      "channel_title": "Programiz",
      "description": "Is learning to code still worth it in 2025? Without a doubt. Learning coding is not just about programming; it's about becoming a ...",
      "published_at": "2025-04-21T12:15:07Z",
      "thumbnail_url": "https://i.ytimg.com/vi/WTfn7dIddt8/hqdefault.jpg"
    },
    {
      "title": "How to Hide Passwords &amp; Credit Card Numbers (with Python) #shorts",
      "video_id": "WLQVdpbVJJs",
      "channel_title": "Programiz",
      "description": "Ever wondered how websites hide your passwords and credit card numbers with asterisks (****)? In just 3 lines of Python, you'll ...",
      "published_at": "2025-02-14T10:24:04Z",
      "thumbnail_url": "https://i.ytimg.com/vi/WLQVdpbVJJs/hqdefault.jpg"
    },
    {
      "title": "Black Friday Exclusive: 60% off on Programiz PRO! #blackfridaydeal #coding",
      "video_id": "TgBF5NXWuwQ",
      "channel_title": "Programiz",
      "description": "This Black Friday, get 60% OFF on Programiz PRO! ✨ End the year strong with our only deal of 2024. Pay once and get lifetime ...",
      "published_at": "2024-11-14T08:00:18Z",
      "thumbnail_url": "https://i.ytimg.com/vi/TgBF5NXWuwQ/hqdefault.jpg"
    },
    {
      "title": "Relationship network of Harry Potter using Python | Shorts",
      "video_id": "TO_UqGXyNN0",
      "channel_title": "Programiz",
      "description": "Relationship network of Harry Potter using Python Create captivating relationship network with ease on Programiz PRO ...",
      "published_at": "2023-06-23T15:05:08Z",
      "thumbnail_url": "https://i.ytimg.com/vi/TO_UqGXyNN0/hqdefault.jpg"
    },
    {
      "title": "Can You Conquer the #ProgramizSummerChallenge in Just 3 Months?",
      "video_id": "3mXk-w7_-Bk",
      "channel_title": "Programiz",
      "description": "Learn to code from scratch and challenge your skills this summer. We have launched #ProgramizSummerChallenge to make your ...",
      "published_at": "2023-06-12T10:15:00Z",
      "thumbnail_url": "https://i.ytimg.com/vi/3mXk-w7_-Bk/hqdefault.jpg"
    }
  ]
}