{
  "fetched_at": "2025-08-10T00:33:06.198938",
  "channel_id": "UCYFpniqsDTy6uBaFUH7cWOg",
  "channel_title": "NS Production",
  "count": 10,
  "videos": [
    {
      "title": "#shortvideo",
      "video_id": "ElR25QXVyeQ",
      "channel_title": "NS Production",
      "description": "",
      "published_at": "2025-08-09T20:04:08Z",
      "thumbnail_url": "https://i.ytimg.com/vi/ElR25QXVyeQ/hqdefault.jpg"
    },
    {
      "title": "#shortvideo",
      "video_id": "q0COvklQIFs",
      "channel_title": "NS Production",
      "description": "",
      "published_at": "2025-08-09T14:46:10Z",
      "thumbnail_url": "https://i.ytimg.com/vi/q0COvklQIFs/hqdefault.jpg"
    },
    {
      "title": "#shortvideo",
      "video_id": "zG1kzMWnIRE",
      "channel_title": "NS Production",
      "description": "",
      "published_at": "2025-08-08T18:08:33Z",
      "thumbnail_url": "https://i.ytimg.com/vi/zG1kzMWnIRE/hqdefault.jpg"
    },
    {
      "title": "Khachatryans - You Broke My Heart",
      "video_id": "E2QZ2mqAk9E",
      "channel_title": "NS Production",
      "description": "You Broke My Heart - Khachatryans Music: Khachatryans Video: NS Production. ☑NS Production ○Social Networks▽ ...",
      "published_at": "2025-08-08T17:00:06Z",
      "thumbnail_url": "https://i.ytimg.com/vi/E2QZ2mqAk9E/hqdefault.jpg"
    },
    {
      "title": "#shortvideo",
      "video_id": "LLIBG51URcI",
      "channel_title": "NS Production",
      "description": "",
      "published_at": "2025-08-08T09:00:52Z",
      "thumbnail_url": "https://i.ytimg.com/vi/LLIBG51URcI/hqdefault.jpg"
    },
    {
      "title": "#shortvideo",
      "video_id": "Mrch_kj72Zs",
      "channel_title": "NS Production",
      "description": "",
      "published_at": "2025-08-08T07:38:48Z",
      "thumbnail_url": "https://i.ytimg.com/vi/Mrch_kj72Zs/hqdefault.jpg"
    },
    {
      "title": "#shortvideo",
      "video_id": "bx290JFoHao",
      "channel_title": "NS Production",
      "description": "",
      "published_at": "2025-08-07T21:57:43Z",
      "thumbnail_url": "https://i.ytimg.com/vi/bx290JFoHao/hqdefault.jpg"
    },
    {
      "title": "#shortvideo",
      "video_id": "Cr_N5AMK38Q",
      "channel_title": "NS Production",
      "description": "",
      "published_at": "2025-08-07T20:06:53Z",
      "thumbnail_url": "https://i.ytimg.com/vi/Cr_N5AMK38Q/hqdefault.jpg"
    },
    {
      "title": "#shortvideo",
      "video_id": "qHuJKv9ejxg",
      "channel_title": "NS Production",
      "description": "",
      "published_at": "2025-08-07T19:33:04Z",
      "thumbnail_url": "https://i.ytimg.com/vi/qHuJKv9ejxg/hqdefault.jpg"
    },
    {
      "title": "#shortvideo",
      "video_id": "YHoCDPMG7DY",
      "channel_title": "NS Production",
      "description": "",
      "published_at": "2025-08-07T19:07:57Z",
      "thumbnail_url": "https://i.ytimg.com/vi/YHoCDPMG7DY/hqdefault.jpg"
    }
  ]
}