{
  "fetched_at": "2025-06-29T00:32:11.170040",
  "channel_id": "UCZGNLDywn8hgzqrC9Mlz_Pw",
  "channel_title": "Tai Lopez",
  "count": 10,
  "videos": [
    {
      "title": "Sit in a chair with a notepad and pen and think deeply.",
      "video_id": "yDqr-9Gzz5E",
      "channel_title": "Tai Lopez",
      "description": "Whenever you feel lost, sit in a chair and write out 100 brainstormed solutions to your problem.",
      "published_at": "2025-06-28T21:08:30Z",
      "thumbnail_url": "https://i.ytimg.com/vi/yDqr-9Gzz5E/hqdefault.jpg"
    },
    {
      "title": "Don&#39;t throw your pearls to swine, because they will eat the pearls and turn to bite you.",
      "video_id": "iHJtu3o7Y7A",
      "channel_title": "Tai Lopez",
      "description": "You can lead a horse to water, but you can't make it drink. Don't try to teach a pig to fly. You can't do it, and it bothers the pig.",
      "published_at": "2025-06-28T19:00:42Z",
      "thumbnail_url": "https://i.ytimg.com/vi/iHJtu3o7Y7A/hqdefault.jpg"
    },
    {
      "title": "If you&#39;re broke, learn sales... (Check in the description)",
      "video_id": "MBkBUoMRolU",
      "channel_title": "Tai Lopez",
      "description": "Become a black belt in sales. https://www.tailopez.com/blackbeltyt.",
      "published_at": "2025-06-28T17:08:47Z",
      "thumbnail_url": "https://i.ytimg.com/vi/MBkBUoMRolU/hqdefault.jpg"
    },
    {
      "title": "Don’t throw your pearls to swine.",
      "video_id": "GA-AVfCiPM8",
      "channel_title": "Tai Lopez",
      "description": "Don't share your knowledge with people who aren't ready to listen.",
      "published_at": "2025-06-27T21:39:39Z",
      "thumbnail_url": "https://i.ytimg.com/vi/GA-AVfCiPM8/hqdefault.jpg"
    },
    {
      "title": "Power tends to corrupt and absolute power corrupts absolutely.",
      "video_id": "eRKPzcHYUMc",
      "channel_title": "Tai Lopez",
      "description": "The craziest thing about politics...",
      "published_at": "2025-06-27T18:29:26Z",
      "thumbnail_url": "https://i.ytimg.com/vi/eRKPzcHYUMc/hqdefault.jpg"
    },
    {
      "title": "$10 billion in cash but with no status, or $1 million and you&#39;re famous in a good way?",
      "video_id": "m1udi7MQQjg",
      "channel_title": "Tai Lopez",
      "description": "",
      "published_at": "2025-06-27T13:17:27Z",
      "thumbnail_url": "https://i.ytimg.com/vi/m1udi7MQQjg/hqdefault.jpg"
    },
    {
      "title": "Just jump right into it and the next thing you know it will be halfway done.",
      "video_id": "JDm-pg_2VI0",
      "channel_title": "Tai Lopez",
      "description": "The key to overcoming laziness is not overthinking it. It always seems harder in your head than it actually is. Just jump right into it ...",
      "published_at": "2025-06-26T16:38:37Z",
      "thumbnail_url": "https://i.ytimg.com/vi/JDm-pg_2VI0/hqdefault.jpg"
    },
    {
      "title": "The greatest general of all time, Napoleon Bonaparte.",
      "video_id": "zIEUctIvs-Q",
      "channel_title": "Tai Lopez",
      "description": "You go into the jungle - even the greatest fall. Even someone like Elon Musk might not be remembered in 20 years.",
      "published_at": "2025-06-26T12:48:58Z",
      "thumbnail_url": "https://i.ytimg.com/vi/zIEUctIvs-Q/hqdefault.jpg"
    },
    {
      "title": "The luckiest thing that will ever happen to you for making money is who you will accidentally meet.",
      "video_id": "IGBK5Vw41PQ",
      "channel_title": "Tai Lopez",
      "description": "2 days left in my European mastermind here in Copenhagen, Denmark. Get tickets to meet me in Copenhagen, Denmark.",
      "published_at": "2025-06-26T00:01:15Z",
      "thumbnail_url": "https://i.ytimg.com/vi/IGBK5Vw41PQ/hqdefault.jpg"
    },
    {
      "title": "Life Is a Performance: Stop Whining or Go Extinct",
      "video_id": "FpenHoRi0OI",
      "channel_title": "Tai Lopez",
      "description": "Text or WhatsApp “hug your neck” to +1 (786) 730-8374 and tell Tai about your goals. In this intense behind-the-scenes Zoom call ...",
      "published_at": "2025-06-25T23:05:34Z",
      "thumbnail_url": "https://i.ytimg.com/vi/FpenHoRi0OI/hqdefault.jpg"
    }
  ]
}